kailash_kaizen-1.0.1.dist-info/licenses/LICENSE
kaizen/__init__.py
kaizen/agent.py
kaizen/agent_config.py
kaizen/agent_types.py
kaizen/rich_output.py
kaizen/smart_defaults.py
kaizen/agents/__init__.py
kaizen/agents/nodes.py
kaizen/agents/register_builtin.py
kaizen/agents/registry.py
kaizen/agents/autonomous/__init__.py
kaizen/agents/autonomous/base.py
kaizen/agents/autonomous/claude_code.py
kaizen/agents/autonomous/codex.py
kaizen/agents/coordination/__init__.py
kaizen/agents/multi_modal/__init__.py
kaizen/agents/multi_modal/document_extraction_agent.py
kaizen/agents/multi_modal/multi_modal_agent.py
kaizen/agents/multi_modal/transcription_agent.py
kaizen/agents/multi_modal/vision_agent.py
kaizen/agents/specialized/__init__.py
kaizen/agents/specialized/batch_processing.py
kaizen/agents/specialized/chain_of_thought.py
kaizen/agents/specialized/code_generation.py
kaizen/agents/specialized/human_approval.py
kaizen/agents/specialized/memory_agent.py
kaizen/agents/specialized/pev.py
kaizen/agents/specialized/planning.py
kaizen/agents/specialized/rag_research.py
kaizen/agents/specialized/react.py
kaizen/agents/specialized/resilient.py
kaizen/agents/specialized/self_reflection.py
kaizen/agents/specialized/simple_qa.py
kaizen/agents/specialized/streaming_chat.py
kaizen/agents/specialized/tree_of_thoughts.py
kaizen/api/__init__.py
kaizen/api/agent.py
kaizen/api/config.py
kaizen/api/presets.py
kaizen/api/result.py
kaizen/api/shortcuts.py
kaizen/api/types.py
kaizen/api/validation.py
kaizen/audio/__init__.py
kaizen/audio/whisper_processor.py
kaizen/config/__init__.py
kaizen/config/providers.py
kaizen/coordination/__init__.py
kaizen/coordination/patterns.py
kaizen/coordination/teams.py
kaizen/core/__init__.py
kaizen/core/agents.py
kaizen/core/base_agent.py
kaizen/core/config.py
kaizen/core/framework.py
kaizen/core/interfaces.py
kaizen/core/kaizen_options.py
kaizen/core/schema_factory.py
kaizen/core/specialist_types.py
kaizen/core/structured_output.py
kaizen/core/token_counter.py
kaizen/core/tool_formatters.py
kailash_kaizen-1.0.1.dist-info/METADATA
kailash_kaizen-1.0.1.dist-info/WHEEL
kailash_kaizen-1.0.1.dist-info/top_level.txt
kailash_kaizen-1.0.1.dist-info/RECORD
