Metadata-Version: 2.4
Name: kailash-kaizen
Version: 1.0.1
Summary: Advanced AI agent framework built on Kailash SDK
Home-page: https://github.com/Integrum-Global/kailash_python_sdk
Author: Kailash Team
Author-email: info@integrum.com
License: Apache-2.0 WITH Additional-Terms
Project-URL: Homepage, https://github.com/Integrum-Global/kailash_python_sdk
Project-URL: Documentation, https://docs.kailash.com/kaizen
Project-URL: Repository, https://github.com/Integrum-Global/kailash_python_sdk
Project-URL: Issues, https://github.com/Integrum-Global/kailash_python_sdk/issues
Keywords: kailash,ai,agents,workflow,automation,signature-programming
Classifier: Development Status :: 5 - Production/Stable
Classifier: Intended Audience :: Developers
Classifier: License :: OSI Approved :: Apache Software License
Classifier: Programming Language :: Python :: 3
Classifier: Programming Language :: Python :: 3.11
Classifier: Programming Language :: Python :: 3.12
Classifier: Programming Language :: Python :: 3.13
Classifier: Topic :: Software Development :: Libraries :: Python Modules
Classifier: Topic :: Scientific/Engineering :: Artificial Intelligence
Classifier: Operating System :: OS Independent
Requires-Python: >=3.11
License-File: LICENSE
Requires-Dist: kailash>=0.10.15
Requires-Dist: pydantic>=2.0.0
Requires-Dist: typing-extensions>=4.5.0
Requires-Dist: PyJWT>=2.8.0
Requires-Dist: bcrypt>=4.0.0
Requires-Dist: redis>=5.0.0
Provides-Extra: dev
Requires-Dist: pytest>=7.0; extra == "dev"
Requires-Dist: pytest-asyncio>=0.21; extra == "dev"
Requires-Dist: pytest-cov>=4.0; extra == "dev"
Requires-Dist: black>=23.0; extra == "dev"
Requires-Dist: isort>=5.12; extra == "dev"
Requires-Dist: ruff>=0.1.0; extra == "dev"
Requires-Dist: fakeredis>=2.20.0; extra == "dev"
Provides-Extra: azure
Requires-Dist: azure-ai-inference>=1.0.0b9; extra == "azure"
Requires-Dist: azure-identity>=1.15.0; extra == "azure"
Requires-Dist: azure-core>=1.38.0; extra == "azure"
Requires-Dist: aiohttp>=3.13.3; extra == "azure"
Provides-Extra: tokens
Requires-Dist: tiktoken>=0.5.0; extra == "tokens"
Provides-Extra: google
Requires-Dist: google-genai>=1.0.0; extra == "google"
Dynamic: author-email
Dynamic: home-page
Dynamic: license-file
Dynamic: requires-python
